windsweeper/__init__.py
windsweeper/_version.py
windsweeper/cli.py
windsweeper/client.py
windsweeper/feedback.py
windsweeper/benchmark/__init__.py
windsweeper/benchmark/benchmark.py
windsweeper/benchmark/examples.py
windsweeper/cli/__init__.py
windsweeper/cli/main.py
windsweeper/cli/commands/__init__.py
windsweeper/cli/commands/create.py
windsweeper/cli/commands/docs.py
windsweeper/cli/commands/generate.py
windsweeper/cli/commands/health.py
windsweeper/cli/commands/init.py
windsweeper/cli/commands/rules.py
windsweeper/cli/commands/serve.py
windsweeper/extensions/__init__.py
windsweeper/extensions/extension.py
windsweeper/monitoring/__init__.py
windsweeper/monitoring/telemetry.py
windsweeper/tests/__init__.py
windsweeper/tests/test_client.py
windsweeper/tests/test_client_additional.py
windsweeper/tests/test_client_methods.py
windsweeper/tests/integration/test_client_integration.py
windsweeper-0.2.1.dist-info/licenses/LICENSE
windsweeper-0.2.1.dist-info/METADATA
windsweeper-0.2.1.dist-info/WHEEL
windsweeper-0.2.1.dist-info/top_level.txt
windsweeper-0.2.1.dist-info/RECORD
