Metadata-Version: 2.4
Name: windsweeper
Version: 0.2.1
Summary: Python SDK for Windsweeper MCP
Home-page: https://github.com/windsweeper/windsweeper
Author: Windsweeper Team
Author-email: Windsweeper Team <team@windsweeper.io>
License: MIT
Project-URL: Homepage, https://github.com/windsweeper/windsweeper
Project-URL: Repository, https://github.com/windsweeper/windsweeper
Project-URL: Documentation, https://docs.windsweeper.io
Classifier: Development Status :: 3 - Alpha
Classifier: Intended Audience :: Developers
Classifier: License :: OSI Approved :: MIT License
Classifier: Programming Language :: Python :: 3
Classifier: Programming Language :: Python :: 3.8
Classifier: Programming Language :: Python :: 3.9
Classifier: Programming Language :: Python :: 3.10
Classifier: Programming Language :: Python :: 3.11
Requires-Python: >=3.8
License-File: LICENSE
Requires-Dist: requests<3.0.0,>=2.31.0
Requires-Dist: pydantic<3.0.0,>=2.0.0
Requires-Dist: click<9.0.0,>=8.1.7
Provides-Extra: dev
Requires-Dist: pytest<8.0.0,>=7.0.0; extra == "dev"
Requires-Dist: pytest-cov<5.0.0,>=4.0.0; extra == "dev"
Requires-Dist: black<24.0.0,>=23.0.0; extra == "dev"
Requires-Dist: isort<6.0.0,>=5.0.0; extra == "dev"
Requires-Dist: mypy<2.0.0,>=1.0.0; extra == "dev"
Requires-Dist: flake8<7.0.0,>=6.0.0; extra == "dev"
Requires-Dist: pre-commit<4.0.0,>=3.0.0; extra == "dev"
Provides-Extra: test
Requires-Dist: pytest<8.0.0,>=7.0.0; extra == "test"
Requires-Dist: pytest-cov<5.0.0,>=4.0.0; extra == "test"
Requires-Dist: pytest-mock<4.0.0,>=3.10.0; extra == "test"
Provides-Extra: docs
Requires-Dist: sphinx<7.0.0,>=6.0.0; extra == "docs"
Requires-Dist: sphinx-rtd-theme<2.0.0,>=1.0.0; extra == "docs"
Requires-Dist: myst-parser<2.0.0,>=1.0.0; extra == "docs"
Requires-Dist: sphinx-autodoc-typehints<2.0.0,>=1.19.0; extra == "docs"
Requires-Dist: sphinx-copybutton<0.6.0,>=0.5.0; extra == "docs"
Requires-Dist: sphinxcontrib-mermaid<0.8.0,>=0.7.1; extra == "docs"
Requires-Dist: sphinx-autobuild<2022.0.0,>=2021.3.14; extra == "docs"
Dynamic: author
Dynamic: home-page
Dynamic: license-file
Dynamic: requires-python
